ucid/__init__.py
ucid/cli.py
ucid/py.typed
ucid/api/__init__.py
ucid/api/app.py
ucid/api/dependencies.py
ucid/api/errors.py
ucid/api/middleware.py
ucid/api/models.py
ucid/api/routes.py
ucid/client/__init__.py
ucid/client/async_client.py
ucid/client/client.py
ucid/client/exceptions.py
ucid/client/models.py
ucid/compute/__init__.py
ucid/compute/backpressure.py
ucid/compute/base.py
ucid/compute/chunking.py
ucid/compute/dask_backend.py
ucid/compute/local.py
ucid/compute/ray_backend.py
ucid/contexts/__init__.py
ucid/contexts/base.py
ucid/contexts/climate.py
ucid/contexts/equity.py
ucid/contexts/fifteen_minute.py
ucid/contexts/registry.py
ucid/contexts/transit.py
ucid/contexts/utils.py
ucid/contexts/vitality.py
ucid/contexts/walkability.py
ucid/core/__init__.py
ucid/core/constants.py
ucid/core/errors.py
ucid/core/models.py
ucid/core/parser.py
ucid/core/registry.py
ucid/core/validator.py
ucid/data/__init__.py
ucid/data/cache.py
ucid/data/gtfs.py
ucid/data/osm.py
ucid/data/population.py
ucid/data/provenance.py
ucid/data/raster.py
ucid/data/sources.py
ucid/i18n/__init__.py
ucid/i18n/locales.py
ucid/i18n/messages.py
ucid/i18n/translations.py
ucid/io/__init__.py
ucid/io/csv.py
ucid/io/geojson.py
ucid/io/geoparquet.py
ucid/io/parquet.py
ucid/io/postgis.py
ucid/io/schemas.py
ucid/ml/__init__.py
ucid/ml/baselines.py
ucid/ml/calibration.py
ucid/ml/drift.py
ucid/ml/evaluation.py
ucid/ml/features.py
ucid/ml/model_cards.py
ucid/ml/predictors.py
ucid/ml/transfer.py
ucid/monitoring/__init__.py
ucid/monitoring/alerts.py
ucid/monitoring/health.py
ucid/monitoring/metrics.py
ucid/monitoring/tracing.py
ucid/realtime/__init__.py
ucid/realtime/eventstore.py
ucid/realtime/hsl.py
ucid/realtime/ingestor.py
ucid/realtime/schemas.py
ucid/realtime/stubs.py
ucid/realtime/windowing.py
ucid/scoring/__init__.py
ucid/scoring/calibration.py
ucid/scoring/grading.py
ucid/scoring/normalization.py
ucid/scoring/sensitivity.py
ucid/scoring/uncertainty.py
ucid/spatial/__init__.py
ucid/spatial/aggregation.py
ucid-1.0.3.dist-info/licenses/AUTHORS
ucid-1.0.3.dist-info/licenses/LICENSE
ucid-1.0.3.dist-info/METADATA
ucid-1.0.3.dist-info/WHEEL
ucid-1.0.3.dist-info/entry_points.txt
ucid-1.0.3.dist-info/top_level.txt
ucid-1.0.3.dist-info/RECORD
