Metadata-Version: 2.4
Name: UCID
Version: 1.0.3
Summary: Urban Context Identifier - A standardized temporal identifier system for comprehensive urban context analysis across global cities
Author-email: UCID Foundation <contact@ucid.org>
Maintainer-email: UCID Foundation <contact@ucid.org>
License: EUPL-1.2
Project-URL: PyPI, https://pypi.org/project/UCID/
Project-URL: Homepage, https://github.com/ucid-foundation/ucid
Project-URL: Repository, https://github.com/ucid-foundation/ucid
Project-URL: Source Code, https://github.com/ucid-foundation/ucid
Project-URL: Download, https://github.com/ucid-foundation/ucid/releases
Project-URL: Documentation, https://ucid-foundation.github.io/ucid
Project-URL: Docs, https://ucid-foundation.github.io/ucid
Project-URL: Changelog, https://github.com/ucid-foundation/ucid/blob/main/CHANGELOG.md
Project-URL: Release Notes, https://github.com/ucid-foundation/ucid/releases
Project-URL: Bug Tracker, https://github.com/ucid-foundation/ucid/issues
Project-URL: Issues, https://github.com/ucid-foundation/ucid/issues
Project-URL: Funding, https://github.com/sponsors/ucid-foundation
Project-URL: Sponsor, https://github.com/sponsors/ucid-foundation
Project-URL: Codecov, https://codecov.io/gh/ucid-foundation/ucid
Project-URL: CI, https://github.com/ucid-foundation/ucid/actions
Project-URL: Python, https://www.python.org/
Keywords: urban-planning,urban-analysis,city-planning,gis,geospatial,spatial-analysis,h3,hexagonal-grid,15-minute-city,walkability,transit,public-transportation,gtfs,openstreetmap,osm,climate,heat-island,equity,accessibility,livability,smart-city,sustainable-cities,urban-mobility,geodata,temporal-analysis
Classifier: Development Status :: 5 - Production/Stable
Classifier: Intended Audience :: Science/Research
Classifier: Intended Audience :: Developers
Classifier: Intended Audience :: Education
Classifier: Intended Audience :: Information Technology
Classifier: License :: OSI Approved :: European Union Public Licence 1.2 (EUPL 1.2)
Classifier: Operating System :: OS Independent
Classifier: Programming Language :: Python :: 3
Classifier: Programming Language :: Python :: 3 :: Only
Classifier: Programming Language :: Python :: 3.11
Classifier: Programming Language :: Python :: 3.12
Classifier: Programming Language :: Python :: 3.13
Classifier: Programming Language :: Python :: Implementation :: CPython
Classifier: Topic :: Scientific/Engineering
Classifier: Topic :: Scientific/Engineering :: GIS
Classifier: Topic :: Scientific/Engineering :: Information Analysis
Classifier: Topic :: Scientific/Engineering :: Visualization
Classifier: Topic :: Software Development :: Libraries :: Python Modules
Classifier: Framework :: FastAPI
Classifier: Natural Language :: English
Classifier: Typing :: Typed
Requires-Python: <3.14,>=3.11
License-File: LICENSE
License-File: AUTHORS
Requires-Dist: numpy<3.0.0,>=1.24.0
Requires-Dist: pandas<3.0.0,>=2.0.0
Requires-Dist: geopandas<2.0.0,>=0.14.0
Requires-Dist: shapely<3.0.0,>=2.0.0
Requires-Dist: pyproj<4.0.0,>=3.5.0
Requires-Dist: h3<5.0.0,>=3.7.0
Requires-Dist: pydantic<3.0.0,>=2.5.0
Requires-Dist: python-dateutil<3.0.0,>=2.8.0
Requires-Dist: click<9.0.0,>=8.0.0
Requires-Dist: httpx<1.0.0,>=0.25.0
Provides-Extra: contexts
Requires-Dist: osmnx<2.0.0,>=1.8.0; extra == "contexts"
Requires-Dist: networkx<4.0.0,>=3.1.0; extra == "contexts"
Provides-Extra: ml
Requires-Dist: scikit-learn<2.0.0,>=1.3.0; extra == "ml"
Requires-Dist: xgboost<3.0.0,>=2.0.0; extra == "ml"
Provides-Extra: temporal
Requires-Dist: statsmodels<1.0.0,>=0.14.0; extra == "temporal"
Provides-Extra: dask
Requires-Dist: dask[complete]<2026.0.0,>=2023.10.0; extra == "dask"
Provides-Extra: ray
Requires-Dist: ray[default]<3.0.0,>=2.8.0; extra == "ray"
Provides-Extra: raster
Requires-Dist: rasterio<2.0.0,>=1.3.0; extra == "raster"
Provides-Extra: api
Requires-Dist: fastapi<1.0.0,>=0.104.0; extra == "api"
Requires-Dist: uvicorn[standard]<1.0.0,>=0.24.0; extra == "api"
Provides-Extra: db
Requires-Dist: psycopg2-binary<3.0.0,>=2.9.0; extra == "db"
Requires-Dist: sqlalchemy<3.0.0,>=2.0.0; extra == "db"
Requires-Dist: geoalchemy2<1.0.0,>=0.14.0; extra == "db"
Provides-Extra: viz
Requires-Dist: matplotlib<4.0.0,>=3.7.0; extra == "viz"
Requires-Dist: plotly<7.0.0,>=5.17.0; extra == "viz"
Requires-Dist: folium<1.0.0,>=0.15.0; extra == "viz"
Provides-Extra: dev
Requires-Dist: pytest<9.0.0,>=7.4.0; extra == "dev"
Requires-Dist: pytest-cov<6.0.0,>=4.1.0; extra == "dev"
Requires-Dist: pytest-benchmark<5.0.0,>=4.0.0; extra == "dev"
Requires-Dist: hypothesis<7.0.0,>=6.92.0; extra == "dev"
Requires-Dist: mypy<2.0.0,>=1.7.0; extra == "dev"
Requires-Dist: ruff<1.0.0,>=0.1.9; extra == "dev"
Requires-Dist: pre-commit<4.0.0,>=3.5.0; extra == "dev"
Provides-Extra: docs
Requires-Dist: sphinx<9.0.0,>=7.2.0; extra == "docs"
Requires-Dist: sphinx-rtd-theme<3.0.0,>=2.0.0; extra == "docs"
Requires-Dist: myst-parser<5.0.0,>=2.0.0; extra == "docs"
Requires-Dist: nbsphinx<1.0.0,>=0.9.0; extra == "docs"
Provides-Extra: security
Requires-Dist: pip-audit<3.0.0,>=2.6.0; extra == "security"
Requires-Dist: bandit<2.0.0,>=1.7.0; extra == "security"
Requires-Dist: cyclonedx-bom<5.0.0,>=4.0.0; extra == "security"
Provides-Extra: all
Requires-Dist: UCID[api,contexts,dask,db,ml,raster,ray,temporal,viz]; extra == "all"
Dynamic: license-file
